rdstation_api_helper/__init__.py
rdstation_api_helper/client.py
rdstation_api_helper/exceptions.py
rdstation_api_helper/py.typed
rdstation_api_helper/retry.py
rdstation_api_helper/utils.py
rdstation_api_helper-1.1.6.dist-info/LICENSE
rdstation_api_helper-1.1.6.dist-info/METADATA
rdstation_api_helper-1.1.6.dist-info/WHEEL
rdstation_api_helper-1.1.6.dist-info/RECORD
