Metadata-Version: 2.3
Name: rdstation-api-helper
Version: 1.1.6
Summary: ETL module for RD Station API database-optimized DataFrame processing
License: GPL
Keywords: rd-station,pandas,etl,data-extraction,reports
Author: Joao Brito
Requires-Python: >=3.11,<3.15
Classifier: Development Status :: 4 - Beta
Classifier: Intended Audience :: Developers
Classifier: Intended Audience :: Information Technology
Classifier: License :: OSI Approved :: GNU General Public License v3 (GPLv3)
Classifier: Operating System :: OS Independent
Classifier: Programming Language :: Python :: 3
Classifier: Programming Language :: Python :: 3.11
Classifier: Programming Language :: Python :: 3.12
Classifier: Topic :: Software Development :: Libraries :: Python Modules
Classifier: Topic :: Internet :: WWW/HTTP :: Dynamic Content
Classifier: Typing :: Typed
Provides-Extra: dev
Requires-Dist: mypy (>=1.0.0) ; extra == "dev"
Requires-Dist: pgsql-upserter (>=0.9.2,<0.10.0)
Requires-Dist: psycopg2-binary (>=2.9.10,<3.0.0)
Requires-Dist: pytest (>=8.0.0) ; extra == "dev"
Requires-Dist: python-dotenv (>=1.1.1,<2.0.0)
Requires-Dist: requests (>=2.32.4,<3.0.0)
Project-URL: Homepage, https://github.com/machado000/rdstation-api-helper
Project-URL: Issues, https://github.com/machado000/rdstation-api-helper/issues
